LICENSE
MANIFEST.in
README.md
setup.cfg
setup.py
tox.ini
nuancier_messages/__init__.py
nuancier_messages/base.py
nuancier_messages/thing.py
nuancier_messages.egg-info/PKG-INFO
nuancier_messages.egg-info/SOURCES.txt
nuancier_messages.egg-info/dependency_links.txt
nuancier_messages.egg-info/entry_points.txt
nuancier_messages.egg-info/not-zip-safe
nuancier_messages.egg-info/requires.txt
nuancier_messages.egg-info/top_level.txt
nuancier_messages/tests/__init__.py
nuancier_messages/tests/test_common.py
nuancier_messages/tests/test_thing.py
nuancier_messages/tests/utils.py